Workbook

Sheet README
A1: CO2 → Methanol explicit recycle/separation economics | v3
A2: Removes the free k_loop proxy. Species-resolved recycle/purge, compression OPEX and flow-scaled flash/distillation/loop CAPEX are explicit and anchored to a published process TEA.
A4: What changed | B4: The previous methanol v2 used an uncalibrated k_loop coefficient. v3 explicitly solves steady-state CO2/H2/CH4/CO-like/N2 recycle and purge, fresh H2/CO2 makeup, compression work, catalyst/reactor size, flash/distillation/recycle equipment scaling, FCI/ACC and indirect OPEX.
A5: Primary economic anchor | B5: Processes 2022, 10, 1535: 145 t/h MeOH, 70 bar one-step loop, 2% purge, 54,290 kmol/h recycle, EC=85.5 M€, FCI=415.9 M€, direct OPEX=874.9 M€/y, NPC=1071.8 M€/y; H2=3097.4 €/t, CO2=44.3 €/t, electricity=90 €/MWh.
A6: Catalyst evidence | B6: Gothe et al., ACS Catalysis 2025 Table 3: controlled Re/TiO2 data at 100 bar, CO2/H2=1:4, same GHSV/time-on-stream. Central comparison uses 500 C prereduction at 200 and 250 C.
A7: Critical physical correction | B7: CH4 is not treated as an instantaneous external loss. It remains in the gas loop, accumulates, increases circulation, and leaves only through purge. This is why high methanation changes the loop architecture.
A8: Separation economics | B8: High-pressure MeOH/H2O condensation is represented as full removal of condensables at the separator; gas-side circulation sizes heat exchangers/flash equipment, crude MeOH+H2O flow sizes distillation/pump equipment, and recycle flow sizes the recycle compressor. Variable equipment is scaled from the published Figure 11 EC split.
A9: Central process convention | B9: Headline catalyst comparisons use the source-anchored 2% purge, rather than silently cost-optimizing purge. A full purge sweep is provided because the source itself selected 2% as an engineering compromise between feed loss and circulation/equipment.
A10: Model boundary | B10: This is a transparent source-anchored reduced TEA, not a new Aspen flowsheet. Figure 11 equipment split is digitized approximately and normalized to exact total EC; scaling exponents are explicit assumptions. Re catalyst purchase price is intentionally excluded from headline performance-leverage comparisons because no consistent supported catalyst price is available.
A11: Main result | B11: At 2% purge, 200 C favors 5 wt% Re (~943 vs 967 €/t), while 250 C strongly favors 1 wt% Re (~975 vs 1258 €/t). The reversal is generated by explicit conversion/selectivity → feed/purge/recycle/separation economics, with no free k_loop.

Sheet Controls
A1: Controls and source inputs
A2: Blue = model assumption/changeable; green = imported from primary source; gray = static definition. Derived values are formulas elsewhere.
A4: Control | B4: Value | C4: Units | D4: Source / rationale
A5: Plant MeOH production | B5: 145 | C5: t/h | D5: https://www.mdpi.com/2227-9717/10/8/1535
A6: Operating hours | B6: 8000 | C6: h/y | D6: https://www.mdpi.com/2227-9717/10/8/1535
A7: H2 price | B7: 3097.4 | C7: €/t | D7: https://www.mdpi.com/2227-9717/10/8/1535
A8: CO2 price | B8: 44.3 | C8: €/t | D8: https://www.mdpi.com/2227-9717/10/8/1535
A9: Electricity price | B9: 90 | C9: €/MWh | D9: https://www.mdpi.com/2227-9717/10/8/1535
A10: H2 feed purity | B10: 0.995 | C10: mol fraction | D10: https://www.mdpi.com/2227-9717/10/8/1535
A11: Reference pressure | B11: 70 | C11: bar | D11: https://www.mdpi.com/2227-9717/10/8/1535
A12: Candidate pressure | B12: 100 | C12: bar | D12: https://www.osti.gov/pages/servlets/purl/3005244
A13: H2 feed pressure | B13: 30 | C13: bar | D13: https://www.mdpi.com/2227-9717/10/8/1535
A14: CO2 feed pressure | B14: 1 | C14: bar | D14: https://www.mdpi.com/2227-9717/10/8/1535
A15: Compressor isentropic efficiency | B15: 0.8 | C15: fraction | D15: https://www.mdpi.com/2227-9717/10/8/1535
A16: Compression temperature | B16: 298.15 | C16: K | D16: Transparent isothermal-equivalent reduced model
... A28: Compressor scaling exponent | B28: 0.67 | C28: - | D28: Explicit reduced-model assumption; sensitivity-ready

Sheet EC_Split_Digitized
A1: Published one-step EC split used for equipment scaling
A2: Figure 11(a) bars were digitized approximately as relative pixel lengths and normalized to the exact published EC total of 85.5 M€. This affects allocation/scaling, not baseline total EC.
A4: Equipment | B4: Pixel weight | C4: Normalized EC (M€) | D4: Treatment in v3
A5: Reactor modules | B5: 306 | C5: =Controls!$B$23*B5/SUM($B$5:$B$15) | D5: scale with catalyst mass^0.60 (STY and Re wt%)
A6: Carbon dioxide compressor | B6: 257 | C6: =Controls!$B$23*B6/SUM($B$5:$B$15) | D6: scale with calculated CO2 compression power^0.67
A7: Hydrogen compressor | B7: 94 | C7: =Controls!$B$23*B7/SUM($B$5:$B$15) | D7: scale with calculated H2 compression power^0.67
A8: Reactor preheaters | B8: 27 | C8: =Controls!$B$23*B8/SUM($B$5:$B$15) | D8: scale with reactor-inlet gas flow^0.60
A9: Heat exchangers | B9: 23 | C9: =Controls!$B$23*B9/SUM($B$5:$B$15) | D9: scale with reactor-inlet gas flow^0.60
A10: Furnace & blower | B10: 37 | C10: =Controls!$B$23*B10/SUM($B$5:$B$15) | D10: scale with purge gas flow^0.60
A11: Distillation column | B11: 27 | C11: =Controls!$B$23*B11/SUM($B$5:$B$15) | D11: scale with crude MeOH+H2O flow^0.60
A12: Turbine & generator | B12: 25 | C12: =Controls!$B$23*B12/SUM($B$5:$B$15) | D12: scale with purge gas flow^0.60
A13: Recycle/reflux compressor | B13: 3 | C13: =Controls!$B$23*B13/SUM($B$5:$B$15) | D13: scale with calculated recycle compression power^0.67
A14: Flash drums | B14: 2 | C14: =Controls!$B$23*B14/SUM($B$5:$B$15) | D14: scale with reactor-inlet gas flow^0.60
A15: Pump | B15: 1 | C15: =Controls!$B$23*B15/SUM($B$5:$B$15) | D15: scale with crude liquid flow^0.60
A17: Total | C17: =SUM(C5:C15)

Sheet Candidate_Inputs
A1: Controlled Re/TiO2 catalyst inputs
A2: 500 C prereduction points from Table 3. CO is reported <1%; central carbon closure assigns only the rounded residual after MeOH+CH4 to CO-like recoverable gas.
A4: Candidate | B4: Re wt% | C4: T (C) | D4: STY gMeOH/gRe/h | E4: X_CO2 | F4: S_MeOH | G4: S_CH4 central | H4: S_CO-like closure | I4: CH4 reported | J4: Source treatment
A5: 1 wt% Re | 200 C | B5: 1 | C5: 200 | D5: 55 | E5: 0.19 | F5: 0.99 | G5: 0 | H5: 0.01 | I5: <1% | J5: All points: 100 bar, CO2/H2=1:4; same controlled study.
A6: 5 wt% Re | 200 C | B6: 5 | C6: 200 | D6: 18 | E6: 0.33 | F6: 0.97 | G6: 0.03 | H6: 0 | I6: 3% | J6: All points: 100 bar, CO2/H2=1:4; same controlled study.
A7: 1 wt% Re | 250 C | B7: 1 | C7: 250 | D7: 65 | E7: 0.23 | F7: 0.97 | G7: 0.01 | H7: 0.02 | I7: 1% | J7: All points: 100 bar, CO2/H2=1:4; same controlled study.
A8: 5 wt% Re | 250 C | B8: 5 | C8: 250 | D8: 16 | E8: 0.4 | F8: 0.74 | G8: 0.25 | H8: 0.01 | I8: 25% | J8: All points: 100 bar, CO2/H2=1:4; same controlled study.

Sheet Reference_Benchmark
A1: One-step process benchmark reconstruction
A2: The reduced species loop is calibrated only by a single recycle-flow correction so that the published 2% purge case exactly matches 54,290 kmol/h. Annual economics then reconstruct the published Table 7 NPC.
A4: Metric | B4: Model / formula | C4: Published | D4: Error | E4: Notes
A5: Raw reduced recycle flow | B5: 49403.557 | E5: Before source flow correction
A6: Recycle-flow correction | B6: 1.0989087 | E6: Published recycle / raw reduced balance
A7: Corrected recycle flow | B7: 54290 | C7: 54290 | D7: 0 | E7: Calibration target
A8: Source-reference non-H2/CO2 fraction | B8: 0.068625155 | E8: Model-derived at source 2% purge; used only as diagnostic reference envelope
A9: Feed cost | B9: 679.32798 | E9: H2 + CO2 from explicit steady-state makeup
A10: Compression electricity | B10: 17.935565 | E10: CO2 + H2 + recycle compression
A11: Common direct OPEX residual | B11: 66.07429 | E11: Calibrated residual so annual direct OPEX equals published 874.9 M€/y
A12: Rebuilt FCI | B12: 415.53 | C12: 415.9 | D12: -0.00088963693 | E12: Exact EC × Lang factor
A13: Rebuilt ACC | B13: 53.424998 | C13: 53.5 | D13: -0.0014019088 | E13: Annuity method
A14: Rebuilt annual NPC | B14: 1071.6834 | C14: 1071.8 | D14: -0.00010882225 | E14: Eq. 24 + 28 solved algebraically
A15: Rebuilt NPC per tonne | B15: 923.86497 | C15: 920 | D15: 0.0042010535 | E15: Difference reflects rounded 145 t/h × 8000 h/y versus reported rounded €/t

Sheet Explicit_Loop_2pct
A1: Explicit species loop and source-anchored economics | 2% purge
A2: Every derived quantity below is an Excel formula. CH4, CO-like residual and N2 accumulate in the recycle gas and leave through purge. MeOH/H2O are removed in the condensation/distillation train.
A4: Candidate | B4: X | C4: SMeOH | D4: SCH4 | E4: SCO | F4: STY | G4: Re wt% | H4: CO2 in | I4: H2 in | J4: CH4 prod | K4: CO prod | L4: CO2 out | M4: H2 out | N4: fresh CO2 | O4: fresh H2 | P4: N2 inlet | Q4: CH4 inlet | R4: CO inlet | S4: recycle mol/mol | T4: recycle kmol/h | U4: non-H2/CO2 frac | V4: methane frac | W4: H2 feed €/t | X4: CO2 feed €/t | Y4: compression €/t | Z4: catalyst t | AA4: EC M€ | AB4: sep/loop EC M€ | AC4: FCI M€ | AD4: ACC M€/y | AE4: direct M€/y | AF4: indirect M€/y | AG4: NPC M€/y | AH4: NPC €/t | AI4: crude liquid kmol/h | AJ4: reactor inlet kmol/h | AK4: rank within T
A5: =Candidate_Inputs!A5 | B5: =Candidate_Inputs!E5 | C5: =Candidate_Inputs!F5 | D5: =Candidate_Inputs!G5 | E5: =Candidate_Inputs!H5 | F5: =Candidate_Inputs!D5 | G5: =Candidate_Inputs!B5 | H5: =1/(B5*C5) | I5: =4*H5 | J5: =D5/C5 | K5: =E5/C5 | L5: =(1-B5)*H5 | M5: =I5-(3+4*J5+K5) | N5: =H5-(1-Controls!$B$21)*L5 | O5: =I5-(1-Controls!$B$21)*M5 | P5: =O5*(1-Controls!$B$10)/Controls!$B$10/Controls!$B$21 | Q5: =(1-Controls!$B$21)/Controls!$B$21*J5 | R5: =(1-Controls!$B$21)/Controls!$B$21*K5 | S5: =(1-Controls!$B$21)*(L5+M5+(Q5+J5)+(R5+K5)+P5) | T5: =S5*Reference_Benchmark!$B$6*Controls!$B$5*1000/32.04186 | U5: =(Q5+R5+P5)/(H5+I5+Q5+R5+P5) | V5: =Q5/(H5+I5+Q5+R5+P5) | W5: =O5*2.01588/32.04186*1000*Controls!$B$7/1000 | X5: =N5*44.0095/32.04186*1000*Controls!$B$8/1000 | Y5: 22.970992 | Z5: 263.63636 | AA5: 72.57956 | AB5: 7.2561822 | AC5: 352.73666 | AD5: 45.351612 | AE5: 933.05482 | AF5: 143.27157 | AG5: 1121.678 | AH5: =AG5*1000000/(Controls!$B$5*Controls!$B$6) | AI5: =(1+(J5*2+K5))*Controls!$B$5*1000/32.04186 | AJ5: =(H5+I5+Q5+R5+P5)*Reference_Benchmark!$B$6*Controls!$B$5*1000/32.04186 | AK5: =IF(AH5<AH6,1,2)
A6: =Candidate_Inputs!A6 | B6: =Candidate_Inputs!E6 | C6: =Candidate_Inputs!F6 | D6: =Candidate_Inputs!G6 | E6: =Candidate_Inputs!H6 | F6: =Candidate_Inputs!D6 | G6: =Candidate_Inputs!B6 | H6: =1/(B6*C6) | I6: =4*H6 | J6: =D6/C6 | K6: =E6/C6 | L6: =(1-B6)*H6 | M6: =I6-(3+4*J6+K6) | N6: =H6-(1-Controls!$B$21)*L6 | O6: =I6-(1-Controls!$B$21)*M6 | P6: =O6*(1-Controls!$B$10)/Controls!$B$10/Controls!$B$21 | Q6: =(1-Controls!$B$21)/Controls!$B$21*J6 | R6: =(1-Controls!$B$21)/Controls!$B$21*K6 | S6: =(1-Controls!$B$21)*(L6+M6+(Q6+J6)+(R6+K6)+P6) | T6: =S6*Reference_Benchmark!$B$6*Controls!$B$5*1000/32.04186 | U6: =(Q6+R6+P6)/(H6+I6+Q6+R6+P6) | V6: =Q6/(H6+I6+Q6+R6+P6) | W6: =O6*2.01588/32.04186*1000*Controls!$B$7/1000 | X6: =N6*44.0095/32.04186*1000*Controls!$B$8/1000 | Y6: 22.127342 | Z6: 161.11111 | AA6: 65.125375 | AB6: 6.2792002 | AC6: 316.50932 | AD6: 40.693836 | AE6: 915.94462 | AF6: 137.59245 | AG6: 1094.2309 | AH6: =AG6*1000000/(Controls!$B$5*Controls!$B$6) | AI6: =(1+(J6*2+K6))*Controls!$B$5*1000/32.04186 | AJ6: =(H6+I6+Q6+R6+P6)*Reference_Benchmark!$B$6*Controls!$B$5*1000/32.04186 | AK6: =IF(AH6<AH5,1,2)
A7: =Candidate_Inputs!A7 | B7: =Candidate_Inputs!E7 | C7: =Candidate_Inputs!F7 | D7: =Candidate_Inputs!G7 | E7: =Candidate_Inputs!H7 | F7: =Candidate_Inputs!D7 | G7: =Candidate_Inputs!B7 | H7: =1/(B7*C7) | I7: =4*H7 | J7: =D7/C7 | K7: =E7/C7 | L7: =(1-B7)*H7 | M7: =I7-(3+4*J7+K7) | N7: =H7-(1-Controls!$B$21)*L7 | O7: =I7-(1-Controls!$B$21)*M7 | P7: =O7*(1-Controls!$B$10)/Controls!$B$10/Controls!$B$21 | Q7: =(1-Controls!$B$21)/Controls!$B$21*J7 | R7: =(1-Controls!$B$21)/Controls!$B$21*K7 | S7: =(1-Controls!$B$21)*(L7+M7+(Q7+J7)+(R7+K7)+P7) | T7: =S7*Reference_Benchmark!$B$6*Controls!$B$5*1000/32.04186 | U7: =(Q7+R7+P7)/(H7+I7+Q7+R7+P7) | V7: =Q7/(H7+I7+Q7+R7+P7) | W7: =O7*2.01588/32.04186*1000*Controls!$B$7/1000 | X7: =N7*44.0095/32.04186*1000*Controls!$B$8/1000 | Y7: 22.839802 | Z7: 223.07692 | AA7: 70.431324 | AB7: 6.9784245 | AC7: 342.29623 | AD7: 44.009279 | AE7: 929.54854 | AF7: 141.7932 | AG7: 1115.351 | AH7: =AG7*1000000/(Controls!$B$5*Controls!$B$6) | AI7: =(1+(J7*2+K7))*Controls!$B$5*1000/32.04186 | AJ7: =(H7+I7+Q7+R7+P7)*Reference_Benchmark!$B$6*Controls!$B$5*1000/32.04186 | AK7: =IF(AH7<AH8,1,2)
A8: =Candidate_Inputs!A8 | B8: =Candidate_Inputs!E8 | C8: =Candidate_Inputs!F8 | D8: =Candidate_Inputs!G8 | E8: =Candidate_Inputs!H8 | F8: =Candidate_Inputs!D8 | G8: =Candidate_Inputs!B8 | H8: =1/(B8*C8) | I8: =4*H8 | J8: =D8/C8 | K8: =E8/C8 | L8: =(1-B8)*H8 | M8: =I8-(3+4*J8+K8) | N8: =H8-(1-Controls!$B$21)*L8 | O8: =I8-(1-Controls!$B$21)*M8 | P8: =O8*(1-Controls!$B$10)/Controls!$B$10/Controls!$B$21 | Q8: =(1-Controls!$B$21)/Controls!$B$21*J8 | R8: =(1-Controls!$B$21)/Controls!$B$21*K8 | S8: =(1-Controls!$B$21)*(L8+M8+(Q8+J8)+(R8+K8)+P8) | T8: =S8*Reference_Benchmark!$B$6*Controls!$B$5*1000/32.04186 | U8: =(Q8+R8+P8)/(H8+I8+Q8+R8+P8) | V8: =Q8/(H8+I8+Q8+R8+P8) | W8: =O8*2.01588/32.04186*1000*Controls!$B$7/1000 | X8: =N8*44.0095/32.04186*1000*Controls!$B$8/1000 | Y8: 29.911238 | Z8: 181.25 | AA8: 82.425236 | AB8: 8.4713678 | AC8: 400.58665 | AD8: 51.50372 | AE8: 1227.0464 | AF8: 180.92737 | AG8: 1459.4775 | AH8: =AG8*1000000/(Controls!$B$5*Controls!$B$6) | AI8: =(1+(J8*2+K8))*Controls!$B$5*1000/32.04186 | AJ8: =(H8+I8+Q8+R8+P8)*Reference_Benchmark!$B$6*Controls!$B$5*1000/32.04186 | AK8: =IF(AH8<AH7,1,2)

Sheet Equipment_Breakdown
A1: Explicit equipment-cost response to catalyst performance
A2: Central 2% purge. EC values are calculated from physical capacity ratios and the Figure 11(a) normalized source split. Re catalyst purchase cost is not included.
A4: Equipment | B4: 1% Re 200C | C4: 5% Re 200C | D4: 1% Re 250C | E4: 5% Re 250C | F4: Scaling driver
A5: Reactor modules | B5: 7.7892925 | C5: 5.7965571 | D5: 7.0464052 | E5: 6.2210205 | F5: catalyst mass from plant production / STY / Re wt%
A6: Carbon dioxide compressor | B6: 29.662713 | C6: 29.236323 | D6: 29.730294 | E6: 34.809168 | F6: fresh CO2 compression power
A7: Hydrogen compressor | B7: 13.262975 | C7: 13.093824 | D7: 13.220811 | E7: 16.196054 | F7: fresh H2 compression power
A8: Reactor preheaters | B8: 4.155154 | C8: 3.1892462 | D8: 3.8668798 | E8: 4.778551 | F8: reactor inlet gas circulation
A9: Heat exchangers | B9: 3.5395756 | C9: 2.7167652 | D9: 3.2940088 | E9: 4.0706175 | F9: reactor inlet gas circulation
A10: Furnace & blower | B10: 6.2382258 | C10: 4.4938434 | D10: 5.722175 | E10: 7.1308992 | F10: purge flow
A11: Distillation column | B11: 2.8827989 | C11: 2.9271068 | D11: 2.9095089 | E11: 3.4328627 | F11: crude MeOH + H2O liquid load
A12: Turbine & generator | B12: 4.2150174 | C12: 3.0363807 | D12: 3.8663345 | E12: 4.8181752 | F12: purge flow
A13: Recycle/reflux compressor | B13: 0.41924814 | C13: 0.2906763 | D13: 0.38071167 | E13: 0.48677776 | F13: recycle flow and loop pressure rise
A14: Flash drums | B14: 0.30778919 | C14: 0.23624046 | D14: 0.28643554 | E14: 0.35396674 | F14: reactor outlet/separator gas handling
A15: Pump | B15: 0.10677033 | C15: 0.10841136 | D15: 0.10775959 | E15: 0.12714306 | F15: crude liquid load
A16: Total EC | B16: =SUM(B5:B15) | C16: =SUM(C5:C15) | D16: =SUM(D5:D15) | E16: =SUM(E5:E15)

Sheet Purge_Sweep
A1: Explicit purge sensitivity
A2: No k_loop proxy: every purge point re-solves the species balance and recalculates feed, compression, equipment scaling and NPC. Source reference 2% is the central comparison.
A4: Candidate | B4: Purge | C4: NPC €/t | D4: Recycle kmol/h | E4: Non-H2/CO2 fraction | F4: Methane fraction | G4: H2 feed €/t | H4: Compression €/t | I4: EC M€
A5: 1 wt% Re | 200 C | B5: 0.005 | C5: 895.25487 | D5: 137054.18 | E5: 0.16169278 | F5: 0 | G5: 604.3643 | H5: 21.62034 | I5: 65.864051
A6: 1 wt% Re | 200 C | B6: 0.006 | C6: 900.01515 | D6: 132759.77 | E6: 0.13885547 | F6: 0 | G6: 607.92168 | H6: 21.686747 | I6: 66.317845
A7: 1 wt% Re | 200 C | B7: 0.007 | C7: 904.80084 | D7: 129660.15 | E7: 0.12176619 | F7: 0 | G7: 611.47906 | H7: 21.762802 | I7: 66.786708
A8: 1 wt% Re | 200 C | B8: 0.008 | C8: 909.59745 | D8: 127307.27 | E8: 0.10849739 | F8: 0 | G8: 615.03645 | H8: 21.844886 | I8: 67.259883
A9: 1 wt% Re | 200 C | B9: 0.009 | C9: 914.39757 | D9: 125452.22 | E9: 0.097896721 | F9: 0 | G9: 618.59383 | H9: 21.93099 | I9: 67.73209
A10: 1 wt% Re | 200 C | B10: 0.01 | C10: 919.19727 | D10: 123945.65 | E10: 0.08923293 | F10: 0 | G10: 622.15121 | H10: 22.019908 | I10: 68.200647
A11: 1 wt% Re | 200 C | B11: 0.011 | C11: 923.99435 | D11: 122692.52 | E11: 0.082019614 | F11: 0 | G11: 625.70859 | H11: 22.110873 | I11: 68.664197
A12: 1 wt% Re | 200 C | B12: 0.012 | C12: 928.78762 | D12: 121629.47 | E12: 0.075920656 | F12: 0 | G12: 629.26597 | H12: 22.203372 | I12: 69.122091
A13: 1 wt% Re | 200 C | B13: 0.013 | C13: 933.57643 | D13: 120712.63 | E13: 0.070696343 | F13: 0 | G13: 632.82335 | H13: 22.297052 | I13: 69.574071
A14: 1 wt% Re | 200 C | B14: 0.014 | C14: 938.36046 | D14: 119910.68 | E14: 0.066171115 | F14: 0 | G14: 636.38074 | H14: 22.391659 | I14: 70.0201
A15: 1 wt% Re | 200 C | B15: 0.015 | C15: 943.1396 | D15: 119200.63 | E15: 0.062213451 | F15: 0 | G15: 639.93812 | H15: 22.487009 | I15: 70.460267
A16: 1 wt% Re | 200 C | B16: 0.016 | C16: 947.91385 | D16: 118565.26 | E16: 0.058722874 | F16: 0 | G16: 643.4955 | H16: 22.582961 | I16: 70.894726
... A1588: 5 wt% Re | 250 C | B1588: 0.4 | C1588: 2127.7231 | D1588: 36267.131 | E1588: 0.035835896 | F1588: 0.028924923 | G1588: 1563.6974 | H1588: 47.723626 | I1588: 128.50059

Sheet Engineering_Diagnostic
A1: Methane accumulation / purge diagnostic
A2: The source-reference non-H2/CO2 fraction is not a universal hard limit. It is used as a same-plant reference envelope to quantify how much purge architecture would need to change for each catalyst.
A4: Candidate | B4: At 2%: non-H2/CO2 | C4: At 2%: recycle kmol/h | D4: Purge to source gas fraction | E4: NPC at that purge €/t | F4: Interpretation
A5: 1 wt% Re | 200 C | B5: 0.048093475 | C5: 116546.49 | D5: 0.014 | E5: 938.36046 | F5: High required purge indicates that catalyst byproduct identity forces a different recycle architecture.
A6: 5 wt% Re | 200 C | B6: 0.13064751 | C6: 67467.397 | D6: 0.042 | E6: 996.80643 | F6: High required purge indicates that catalyst byproduct identity forces a different recycle architecture.
A7: 1 wt% Re | 250 C | B7: 0.095252046 | C7: 100925.12 | D7: 0.029 | E7: 996.20019 | F7: High required purge indicates that catalyst byproduct identity forces a different recycle architecture.
A8: 5 wt% Re | 250 C | B8: 0.52080801 | C8: 145648.01 | D8: 0.241 | E8: 1765.139 | F8: High required purge indicates that catalyst byproduct identity forces a different recycle architecture.
A10: Source reference non-H2/CO2 fraction | B10: 0.068625155
A11: Source reference recycle | B11: 54290 | C11: kmol/h

Sheet Methanol_Leverage
A1: Local catalyst-economic leverage within methanol
A2: Local elasticities at the source-anchored 2% purge. L_X and L_STY are beneficial-increase elasticities; L_CH4 is the cost elasticity to CH4 while selectivity is transferred between CH4 and MeOH.
A4: Candidate | B4: L_STY | C4: L_conversion | D4: L_CH4 suppression | E4: Interpretation
A5: 1 wt% Re | 200 C | B5: 0.0047153 | C5: 0.12174196 | E5: A value of 0.10 means a 1% beneficial property change changes system cost by ~0.10% locally.
A6: 5 wt% Re | 200 C | B6: 0.0035970019 | C6: 0.074961604 | D6: 0.035997874 | E6: A value of 0.10 means a 1% beneficial property change changes system cost by ~0.10% locally.
A7: 1 wt% Re | 250 C | B7: 0.0042897854 | C7: 0.1037856 | D7: 0.011898984 | E7: A value of 0.10 means a 1% beneficial property change changes system cost by ~0.10% locally.
A8: 5 wt% Re | 250 C | B8: 0.0028943015 | C8: 0.05882776 | D8: 0.37579392 | E8: A value of 0.10 means a 1% beneficial property change changes system cost by ~0.10% locally.

Sheet Sources
A1: Sources
A2: Primary/authoritative sources and exactly what is taken from each.
A4: Use | B4: URL / local source | C4: What is taken
A5: Detailed methanol process + TEA | B5: https://www.mdpi.com/2227-9717/10/8/1535 | C5: Plant scale; 70 bar; 2% purge; recycle flow; process configuration; catalyst loading; compressor efficiencies; EC/FCI/ACC/OPEX/NPC; feed/electricity prices; Lang factor/economic equations; Figure 11 EC split.
A6: Re/TiO2 catalyst data | B6: https://www.osti.gov/pages/servlets/purl/3005244 | C6: Table 3 conversion, MeOH STY, MeOH/CH4 selectivity and controlled 100 bar CO2/H2=1:4 conditions.
A7: Re/TiO2 bibliographic record | B7: https://www.osti.gov/pages/biblio/3005244 | C7: Publication/DOI metadata.
A8: Ammonia final model | B8: ammonia_final_consistency_closure_v1.xlsx / NH3-FINAL-1.0 | C8: NH3-FINAL-1.0 Fe optimum and reoptimized ±0.5% activity perturbations for local activity-economic leverage.

Sheet Audit
A1: Audit / scope control
A2: Checks required before using v3 as a paper result.
A4: Check | B4: Status | C4: Notes
A5: Free k_loop removed | B5: PASS | C5: Recycle/separation cost is no longer represented by an arbitrary cost coefficient.
A6: Species recycle is explicit | B6: PASS | C6: CH4/CO-like/N2 accumulation, recycle and purge are solved at steady state; fresh H2/CO2 makeup follows from the same mass balance.
A7: Source annual NPC reconstructed | B7: PASS | C7: Model=1071.68 vs source=1071.8 M€/y.
A8: Source recycle flow calibrated | B8: PASS | C8: One scalar flow correction 1.0989 exactly maps the reduced source balance to 54,290 kmol/h; it is then frozen for all candidates.
A9: Product selectivity treatment | B9: PASS | C9: No exact CO value is invented where the catalyst paper says CO<1%; rounded carbon closure is carried as CO-like recoverable gas. 1 wt%/200C CH4<1 is central=0 with a bounded alternative available.
A10: Separation CAPEX explicit | B10: PASS | C10: Heat exchangers/flash/recycle compressor/distillation/pump all scale with explicit gas/liquid flow or compressor power.
A11: Separation utility OPEX | B11: LIMITATION | C11: The source process is heat-integrated; v3 does not invent an external steam tariff. Variable thermal separation duty is represented through equipment scaling, while the source-calibrated direct-OPEX residual remains fixed.
A12: Equipment split precision | B12: LIMITATION | C12: Figure 11 EC category shares are approximate digitization, normalized to exact 85.5 M€ total. This is adequate for reduced sensitivity, not a substitute for the source supplementary equipment table.
A13: Re catalyst purchase price | B13: EXCLUDED BY DESIGN | C13: Headline comparison isolates performance-mediated leverage. A consistent supported Re/TiO2 catalyst manufacturing/recovery cost is not available in the supplied primary catalyst paper.
A14: Global T/P optimization | B14: NOT CLAIMED | C14: Catalyst performance exists only at measured 200/250 C and 100 bar; v3 compares those controlled operating points and propagates process economics. It does not interpolate a new kinetic map.
